Metadata-Version: 1.0
Name: aeschliman
Version: 0.1
Summary: Gaussian/Binomial distributions
Home-page: UNKNOWN
Author: Trevor Aeschliman
Author-email: trevor@dive-data.com
License: UNKNOWN
Platform: UNKNOWN
